[
    {
    "id": 3,
    "name": "Assault Riffle (Bullpup)",
    "color": 3,
    "img": "ar-bullpup.png"
    },
    {
        "detailLevel": 3,
        "weaponId": 3,
        "damage": 32,
        "damageHead": 64,
        "fireRate": 1.75,
        "magazineSize": 30,
        "reloadTime": 2.5,
        "impact": 46,
        "spreadBase": 0.175,
        "spreadSprint": 1.5,
        "spreadJump": 1.25,
        "spreadDownsights": 0.65,
        "spreadStanding": 0.55,
        "spreadCrouching": 0.75,
        "firingRateBurst": 12,
        "environementDamage": 30,
        "recoilHorizontal": 0.25,
        "recoilVertical": 1.6625,
        "recoilMaxAngle": 25,
        "recoilMinAngle": -25,
        "recoilDownsights": 0.8
    },
    {
        "detailLevel": 4,
        "weaponId": 3,
        "damage": 33,
        "damageHead": 66,
        "fireRate": 1.75,
        "magazineSize": 30,
        "reloadTime": 2.3,
        "impact": 48,
        "spreadBase": 0.175,
        "spreadSprint": 1.5,
        "spreadJump": 1.25,
        "spreadDownsights": 0.65,
        "spreadStanding": 0.55,
        "spreadCrouching": 0.75,
        "firingRateBurst": 12,
        "environementDamage": 30,
        "recoilHorizontal": 0.25,
        "recoilVertical": 1.575,
        "recoilMaxAngle": 25,
        "recoilMinAngle": -25,
        "recoilDownsights": 0.8
    }
]